{
    "_repo_id": 13,
    "_repo_name": "CategoricalData/CQL",
    "_total_commits": 91,
    "_commit_history": [
        {
            "_sha_id": "bec1653a1538b3579e23839ccc8de30e17df8b6e",
            "_timestamp": "2019-03-13 00:31:47-04:00",
            "_commit_index": 1,
            "_changed_files_list": []
        },
        {
            "_sha_id": "d4a91cd643bb4ef86f1713655855a49a5b12b97d",
            "_timestamp": "2019-06-26 00:03:07-04:00",
            "_commit_index": 64,
            "_changed_files_list": []
        },
        {
            "_sha_id": "94b7da6cb36a51af0504d96d8492e1bae3ff96dd",
            "_timestamp": "2019-08-22 22:17:06-04:00",
            "_commit_index": 76,
            "_changed_files_list": []
        },
        {
            "_sha_id": "17c3c0750c83d2cc4c8bbbad30055ed843204cb8",
            "_timestamp": "2019-06-13 00:13:16-04:00",
            "_commit_index": 63,
            "_changed_files_list": []
        },
        {
            "_sha_id": "4688006206a03b0e8ccda044dad7ab02720a6bbc",
            "_timestamp": "2019-04-16 03:50:38-04:00",
            "_commit_index": 45,
            "_changed_files_list": []
        },
        {
            "_sha_id": "1d2ac748b6e23cea82e08bdb66620a3173cefadb",
            "_timestamp": "2019-03-13 04:35:22-04:00",
            "_commit_index": 2,
            "_changed_files_list": []
        },
        {
            "_sha_id": "1c136027607d38485da4f91de3992a4ddcb3eea7",
            "_timestamp": "2019-05-08 00:43:30-04:00",
            "_commit_index": 54,
            "_changed_files_list": []
        },
        {
            "_sha_id": "1367d1f7776a1816842190f831d08ac932d9ac73",
            "_timestamp": "2019-05-09 03:16:55-04:00",
            "_commit_index": 55,
            "_changed_files_list": []
        },
        {
            "_sha_id": "1f94a21245145b20ec30bffd876466b794eaa91f",
            "_timestamp": "2019-04-14 00:48:43-04:00",
            "_commit_index": 17,
            "_changed_files_list": []
        },
        {
            "_sha_id": "73505d09f1ec453e92739186721fa4ff2febd495",
            "_timestamp": "2019-11-17 21:06:02-08:00",
            "_commit_index": 91,
            "_changed_files_list": []
        }
    ]
}