{
    "_repo_id": 280,
    "_repo_name": "linkedin/Cubert",
    "_total_commits": 12,
    "_commit_history": [
        {
            "_sha_id": "c68a75020c2721cbff96870e283982c960f29b78",
            "_timestamp": "2014-09-28 15:48:45-07:00",
            "_commit_index": 1,
            "_changed_files_list": []
        },
        {
            "_sha_id": "6bc737974e3174ca6d4e5abcc5277a5dc3b1a8b2",
            "_timestamp": "2014-10-06 12:23:18-07:00",
            "_commit_index": 5,
            "_changed_files_list": [
                {
                    "_file_name": "src/main/java/com/linkedin/cubert/plan/physical/PhysicalParser.java",
                    "_is_antlr_file": true,
                    "_enter_cnt": 11,
                    "_exit_cnt": 44,
                    "_visit_cnt": 0
                }
            ]
        },
        {
            "_sha_id": "4fb0ed3c1b921ca59df33ac9c4d121e218a5156e",
            "_timestamp": "2014-09-28 18:12:42-07:00",
            "_commit_index": 2,
            "_changed_files_list": []
        },
        {
            "_sha_id": "a97d9b63e5abb8af5f62af2aae0d4ab580a6857c",
            "_timestamp": "2014-10-01 17:13:35-07:00",
            "_commit_index": 3,
            "_changed_files_list": [
                {
                    "_file_name": "src/main/java/com/linkedin/cubert/plan/physical/PhysicalParser.java",
                    "_is_antlr_file": true,
                    "_enter_cnt": 11,
                    "_exit_cnt": 44,
                    "_visit_cnt": 0
                }
            ]
        },
        {
            "_sha_id": "02174c68d4b1837165714307dc0d20b236881d8e",
            "_timestamp": "2014-10-02 11:28:43-07:00",
            "_commit_index": 4,
            "_changed_files_list": [
                {
                    "_file_name": "src/main/java/com/linkedin/cubert/plan/physical/PhysicalParser.java",
                    "_is_antlr_file": true,
                    "_enter_cnt": 11,
                    "_exit_cnt": 44,
                    "_visit_cnt": 0
                }
            ]
        },
        {
            "_sha_id": "dd782cb7fe4c6a98644a12d2c485934fc5d19fc1",
            "_timestamp": "2014-11-12 18:43:41-08:00",
            "_commit_index": 6,
            "_changed_files_list": [
                {
                    "_file_name": "src/main/java/com/linkedin/cubert/plan/physical/PhysicalParser.java",
                    "_is_antlr_file": true,
                    "_enter_cnt": 11,
                    "_exit_cnt": 44,
                    "_visit_cnt": 0
                }
            ]
        },
        {
            "_sha_id": "aae8d75ebc872f22458b849272d7137163061ba1",
            "_timestamp": "2014-11-24 14:52:31-08:00",
            "_commit_index": 9,
            "_changed_files_list": [
                {
                    "_file_name": "src/main/java/com/linkedin/cubert/plan/physical/PhysicalParser.java",
                    "_is_antlr_file": true,
                    "_enter_cnt": 11,
                    "_exit_cnt": 46,
                    "_visit_cnt": 0
                }
            ]
        },
        {
            "_sha_id": "260d109442b6159d23b8b4c20d3796217881ec01",
            "_timestamp": "2014-09-28 18:01:21-07:00",
            "_commit_index": 1,
            "_changed_files_list": []
        },
        {
            "_sha_id": "f40f939fd1ed1ea5003eb352d14e0f2226cd097a",
            "_timestamp": "2014-11-12 18:43:53-08:00",
            "_commit_index": 7,
            "_changed_files_list": [
                {
                    "_file_name": "src/main/java/com/linkedin/cubert/plan/physical/PhysicalParser.java",
                    "_is_antlr_file": true,
                    "_enter_cnt": 11,
                    "_exit_cnt": 44,
                    "_visit_cnt": 0
                }
            ]
        },
        {
            "_sha_id": "71782f7029acaae12cbb7e566952e27b63e00daa",
            "_timestamp": "2015-08-24 16:31:49-07:00",
            "_commit_index": 12,
            "_changed_files_list": [
                {
                    "_file_name": "src/main/java/com/linkedin/cubert/plan/physical/PhysicalParser.java",
                    "_is_antlr_file": true,
                    "_enter_cnt": 11,
                    "_exit_cnt": 48,
                    "_visit_cnt": 0
                }
            ]
        }
    ]
}