{
    "_repo_id": 199,
    "_repo_name": "ebean-orm/ebean",
    "_total_commits": 3863,
    "_commit_history": [
        {
            "_sha_id": "2b74d0f9d92673fae5782b71bfbc9dc7a58a1f37",
            "_timestamp": "2012-09-13 04:49:56-07:00",
            "_commit_index": 1,
            "_changed_files_list": []
        },
        {
            "_sha_id": "99bd2972d035e859062f8ee8a476850b09bee89e",
            "_timestamp": "2016-10-17 20:57:26+13:00",
            "_commit_index": 1931,
            "_changed_files_list": []
        },
        {
            "_sha_id": "0aa9208dcc1e6a0e919da24b473547d21c22f502",
            "_timestamp": "2018-05-30 03:36:38+12:00",
            "_commit_index": 2896,
            "_changed_files_list": []
        },
        {
            "_sha_id": "888384f7dbc7dcf5743755368260c9c3a40b4d69",
            "_timestamp": "2019-03-01 18:12:36+13:00",
            "_commit_index": 3379,
            "_changed_files_list": []
        },
        {
            "_sha_id": "502104eba82eb93ccd63ab9b6d6e161630f19b44",
            "_timestamp": "2019-07-17 21:53:14+12:00",
            "_commit_index": 3620,
            "_changed_files_list": []
        },
        {
            "_sha_id": "80a764a448d78c55b6bfd4d169acb8fe64cd6aae",
            "_timestamp": "2019-10-09 00:17:34+13:00",
            "_commit_index": 3741,
            "_changed_files_list": [
                {
                    "_file_name": "src/main/java/io/ebeaninternal/server/grammer/EqlWhereListener.java",
                    "_is_antlr_file": true,
                    "_enter_cnt": 15,
                    "_exit_cnt": 5,
                    "_visit_cnt": 0
                }
            ]
        },
        {
            "_sha_id": "96747115165794c329fca4346ab4135e566d400c",
            "_timestamp": "2019-08-19 21:36:19+12:00",
            "_commit_index": 3680,
            "_changed_files_list": [
                {
                    "_file_name": "src/main/java/io/ebeaninternal/server/grammer/EqlWhereListener.java",
                    "_is_antlr_file": true,
                    "_enter_cnt": 15,
                    "_exit_cnt": 5,
                    "_visit_cnt": 0
                }
            ]
        },
        {
            "_sha_id": "318f6ae3f518570ba3374de85b2e1e2a5887ad70",
            "_timestamp": "2019-07-31 23:21:01+12:00",
            "_commit_index": 3650,
            "_changed_files_list": []
        },
        {
            "_sha_id": "f5459920e97d32cc49496b9a30c637ffef161998",
            "_timestamp": "2019-08-12 21:05:32+12:00",
            "_commit_index": 3665,
            "_changed_files_list": []
        },
        {
            "_sha_id": "ec55b2f096164b6c62e3de5e019971f69ebdb772",
            "_timestamp": "2019-12-24 02:02:11+13:00",
            "_commit_index": 3863,
            "_changed_files_list": [
                {
                    "_file_name": "src/main/java/io/ebeaninternal/server/grammer/EqlWhereListener.java",
                    "_is_antlr_file": true,
                    "_enter_cnt": 15,
                    "_exit_cnt": 5,
                    "_visit_cnt": 0
                }
            ]
        }
    ]
}