{
    "_repo_id": 72,
    "_repo_name": "RubbaBoy/EmojIDE",
    "_total_commits": 71,
    "_commit_history": [
        {
            "_sha_id": "072045061de02ec9fc89b0e02d0845f9675a7926",
            "_timestamp": "2019-08-02 16:01:07-04:00",
            "_commit_index": 1,
            "_changed_files_list": []
        },
        {
            "_sha_id": "d3fa3f2f7a5e9c4067d4c93c25c7edc8bb3ef761",
            "_timestamp": "2019-08-04 21:15:01-04:00",
            "_commit_index": 8,
            "_changed_files_list": []
        },
        {
            "_sha_id": "57c56dc098501c1ffd45098704f00b1bfe0689c1",
            "_timestamp": "2019-08-04 22:55:59-04:00",
            "_commit_index": 9,
            "_changed_files_list": []
        },
        {
            "_sha_id": "8dd52eb6cf32f8c894856d1f7c3c8b8a5b71d0b2",
            "_timestamp": "2019-08-20 20:37:20-04:00",
            "_commit_index": 61,
            "_changed_files_list": []
        },
        {
            "_sha_id": "2caff24979877d6b7ddac71ea53ad44cceb4366f",
            "_timestamp": "2019-08-14 14:11:29-04:00",
            "_commit_index": 34,
            "_changed_files_list": []
        },
        {
            "_sha_id": "0890c188eacf57d6086bb9ece5b8e95dc6fa2559",
            "_timestamp": "2019-08-02 16:33:08-04:00",
            "_commit_index": 1,
            "_changed_files_list": []
        },
        {
            "_sha_id": "568f3b9c47888641bb42dec92a6cc59592aaf194",
            "_timestamp": "2019-08-02 17:53:26-04:00",
            "_commit_index": 2,
            "_changed_files_list": []
        },
        {
            "_sha_id": "93271e49bb6edf4be28e5a22fd68f9436eeed931",
            "_timestamp": "2019-08-07 22:00:15-04:00",
            "_commit_index": 19,
            "_changed_files_list": []
        },
        {
            "_sha_id": "eb13b536414d457a74f3024bc4f2da4539e2d8e6",
            "_timestamp": "2019-08-06 18:56:43-04:00",
            "_commit_index": 14,
            "_changed_files_list": []
        },
        {
            "_sha_id": "c6a452c29df3b1b98a208192f7bec9631f037994",
            "_timestamp": "2019-08-27 22:41:36-04:00",
            "_commit_index": 71,
            "_changed_files_list": []
        }
    ]
}