{
    "_repo_id": 226,
    "_repo_name": "graknlabs/graql",
    "_total_commits": 342,
    "_commit_history": [
        {
            "_sha_id": "0f077a469dc5d413a3940d309df956dca34853f2",
            "_timestamp": "2019-02-16 23:02:45+00:00",
            "_commit_index": 1,
            "_changed_files_list": [
                {
                    "_file_name": "java/parser/Parser.java",
                    "_is_antlr_file": true,
                    "_enter_cnt": 0,
                    "_exit_cnt": 0,
                    "_visit_cnt": 47
                }
            ]
        },
        {
            "_sha_id": "b0d32bf8e374789ca4c384a2ffdfb6903c69d1d8",
            "_timestamp": "2019-03-19 11:50:47+00:00",
            "_commit_index": 90,
            "_changed_files_list": [
                {
                    "_file_name": "java/parser/Parser.java",
                    "_is_antlr_file": true,
                    "_enter_cnt": 0,
                    "_exit_cnt": 0,
                    "_visit_cnt": 47
                }
            ]
        },
        {
            "_sha_id": "72ca58ca6efff207c897e77b869398fee478beb3",
            "_timestamp": "2019-04-14 19:14:27+01:00",
            "_commit_index": 157,
            "_changed_files_list": [
                {
                    "_file_name": "java/parser/Parser.java",
                    "_is_antlr_file": true,
                    "_enter_cnt": 0,
                    "_exit_cnt": 0,
                    "_visit_cnt": 47
                }
            ]
        },
        {
            "_sha_id": "8492ed4daea80e1c5092f985b58b896c0d159d85",
            "_timestamp": "2019-02-26 15:19:11+00:00",
            "_commit_index": 14,
            "_changed_files_list": [
                {
                    "_file_name": "java/parser/Parser.java",
                    "_is_antlr_file": true,
                    "_enter_cnt": 0,
                    "_exit_cnt": 0,
                    "_visit_cnt": 47
                }
            ]
        },
        {
            "_sha_id": "b330b897ec2d2df496f354f677dd7bb7f60f8360",
            "_timestamp": "2019-12-04 21:46:47+00:00",
            "_commit_index": 339,
            "_changed_files_list": [
                {
                    "_file_name": "java/parser/Parser.java",
                    "_is_antlr_file": true,
                    "_enter_cnt": 0,
                    "_exit_cnt": 0,
                    "_visit_cnt": 45
                }
            ]
        },
        {
            "_sha_id": "1c4d1c432ba7cb1be2d1a14b7bc77c2839df69c7",
            "_timestamp": "2019-03-06 12:57:20+00:00",
            "_commit_index": 34,
            "_changed_files_list": [
                {
                    "_file_name": "java/parser/Parser.java",
                    "_is_antlr_file": true,
                    "_enter_cnt": 0,
                    "_exit_cnt": 0,
                    "_visit_cnt": 47
                }
            ]
        },
        {
            "_sha_id": "417c695e9d6fc15c18d920d583c70542b181e8fb",
            "_timestamp": "2019-03-12 16:41:55+00:00",
            "_commit_index": 74,
            "_changed_files_list": [
                {
                    "_file_name": "java/parser/Parser.java",
                    "_is_antlr_file": true,
                    "_enter_cnt": 0,
                    "_exit_cnt": 0,
                    "_visit_cnt": 47
                }
            ]
        },
        {
            "_sha_id": "c831ba27a821cb17c309f1df5024f736b276de5c",
            "_timestamp": "2019-02-24 23:12:37+00:00",
            "_commit_index": 12,
            "_changed_files_list": [
                {
                    "_file_name": "java/parser/Parser.java",
                    "_is_antlr_file": true,
                    "_enter_cnt": 0,
                    "_exit_cnt": 0,
                    "_visit_cnt": 47
                }
            ]
        },
        {
            "_sha_id": "f7a6a75280ad99ab7ebd60e9429584d3c80e2171",
            "_timestamp": "2019-03-19 18:45:50+00:00",
            "_commit_index": 92,
            "_changed_files_list": [
                {
                    "_file_name": "java/parser/Parser.java",
                    "_is_antlr_file": true,
                    "_enter_cnt": 0,
                    "_exit_cnt": 0,
                    "_visit_cnt": 47
                }
            ]
        },
        {
            "_sha_id": "06cf6b7eb4c2c5c4fc424bed38951cc5c595d2f9",
            "_timestamp": "2019-12-15 20:51:07+00:00",
            "_commit_index": 342,
            "_changed_files_list": [
                {
                    "_file_name": "java/parser/Parser.java",
                    "_is_antlr_file": true,
                    "_enter_cnt": 0,
                    "_exit_cnt": 0,
                    "_visit_cnt": 45
                }
            ]
        }
    ]
}