{
    "_repo_id": 393,
    "_repo_name": "tgvaughan/MASTER",
    "_total_commits": 550,
    "_commit_history": [
        {
            "_sha_id": "41964d9f6df306d2257485e700c8bdc0e4ffbb24",
            "_timestamp": "2012-02-15 14:41:50+13:00",
            "_commit_index": 1,
            "_changed_files_list": []
        },
        {
            "_sha_id": "f106c3bd5a46946b4bdcfc54522faa0be1031f75",
            "_timestamp": "2013-02-12 18:40:39+13:00",
            "_commit_index": 274,
            "_changed_files_list": []
        },
        {
            "_sha_id": "286e66af273537181eed2c2792c5e0d8effba795",
            "_timestamp": "2014-04-02 17:50:20+13:00",
            "_commit_index": 411,
            "_changed_files_list": []
        },
        {
            "_sha_id": "135f039f82eb7be6066042548d20dee2cab06cee",
            "_timestamp": "2015-03-16 09:36:33+13:00",
            "_commit_index": 480,
            "_changed_files_list": [
                {
                    "_file_name": "src/master/model/ExpressionEvaluator.java",
                    "_is_antlr_file": true,
                    "_enter_cnt": 0,
                    "_exit_cnt": 0,
                    "_visit_cnt": 14
                },
                {
                    "_file_name": "src/master/utilities/pfe/PFEJSONVisitor.java",
                    "_is_antlr_file": true,
                    "_enter_cnt": 0,
                    "_exit_cnt": 0,
                    "_visit_cnt": 7
                },
                {
                    "_file_name": "src/master/utilities/pfe/PFEVisitor.java",
                    "_is_antlr_file": true,
                    "_enter_cnt": 0,
                    "_exit_cnt": 0,
                    "_visit_cnt": 7
                }
            ]
        },
        {
            "_sha_id": "53eeb1f39cf28a008db0e77eb85ed1e5795ced05",
            "_timestamp": "2014-10-29 12:08:30+01:00",
            "_commit_index": 445,
            "_changed_files_list": [
                {
                    "_file_name": "src/master/utilities/pfe/PFEJSONVisitor.java",
                    "_is_antlr_file": true,
                    "_enter_cnt": 0,
                    "_exit_cnt": 0,
                    "_visit_cnt": 7
                },
                {
                    "_file_name": "src/master/utilities/pfe/PFEVisitor.java",
                    "_is_antlr_file": true,
                    "_enter_cnt": 0,
                    "_exit_cnt": 0,
                    "_visit_cnt": 7
                }
            ]
        },
        {
            "_sha_id": "235d543ce1fea31efc60cd8c6df5c828cae5500d",
            "_timestamp": "2014-06-11 18:31:21+12:00",
            "_commit_index": 428,
            "_changed_files_list": [
                {
                    "_file_name": "src/master/utilities/pfe/PFEJSONVisitor.java",
                    "_is_antlr_file": true,
                    "_enter_cnt": 0,
                    "_exit_cnt": 0,
                    "_visit_cnt": 7
                },
                {
                    "_file_name": "src/master/utilities/pfe/PFEVisitor.java",
                    "_is_antlr_file": true,
                    "_enter_cnt": 0,
                    "_exit_cnt": 0,
                    "_visit_cnt": 7
                }
            ]
        },
        {
            "_sha_id": "3215da8ce557ea1a898ed903f995891ec9af9b56",
            "_timestamp": "2014-04-04 22:02:50+13:00",
            "_commit_index": 419,
            "_changed_files_list": []
        },
        {
            "_sha_id": "ef01d4f6bd65cf0b4f29b0124bdfddb64d5bdc7c",
            "_timestamp": "2014-06-06 16:31:49+12:00",
            "_commit_index": 423,
            "_changed_files_list": []
        },
        {
            "_sha_id": "49b45af8e0cc2aa7649ccda57c6ed8ba25c8d3ed",
            "_timestamp": "2014-06-06 21:34:13+12:00",
            "_commit_index": 425,
            "_changed_files_list": []
        },
        {
            "_sha_id": "54fc53bfe1adfb51e2c4642b23cb0a7addf18781",
            "_timestamp": "2018-11-09 16:40:33+08:00",
            "_commit_index": 550,
            "_changed_files_list": [
                {
                    "_file_name": "src/master/model/PopulationSize.java",
                    "_is_antlr_file": true,
                    "_enter_cnt": 0,
                    "_exit_cnt": 1,
                    "_visit_cnt": 0
                },
                {
                    "_file_name": "src/master/model/ExpressionEvaluator.java",
                    "_is_antlr_file": true,
                    "_enter_cnt": 0,
                    "_exit_cnt": 0,
                    "_visit_cnt": 15
                },
                {
                    "_file_name": "src/master/utilities/pfe/PFEJSONVisitor.java",
                    "_is_antlr_file": true,
                    "_enter_cnt": 0,
                    "_exit_cnt": 0,
                    "_visit_cnt": 7
                },
                {
                    "_file_name": "src/master/utilities/pfe/PFEVisitor.java",
                    "_is_antlr_file": true,
                    "_enter_cnt": 0,
                    "_exit_cnt": 0,
                    "_visit_cnt": 7
                }
            ]
        }
    ]
}