{
    "_repo_id": 236,
    "_repo_name": "harbby/sylph",
    "_total_commits": 520,
    "_commit_history": [
        {
            "_sha_id": "965c3f9ee5227329595366fa329f1acca5de8662",
            "_timestamp": "2018-06-19 13:26:34+08:00",
            "_commit_index": 1,
            "_changed_files_list": []
        },
        {
            "_sha_id": "9b70e81854f5217c51e0081ea5f75c261558d5cb",
            "_timestamp": "2018-11-24 18:59:58+08:00",
            "_commit_index": 259,
            "_changed_files_list": []
        },
        {
            "_sha_id": "906e008d9782bbfbc94d39af21d66d44f795f032",
            "_timestamp": "2019-04-22 12:06:58+08:00",
            "_commit_index": 389,
            "_changed_files_list": []
        },
        {
            "_sha_id": "ae5601cc8b6734b2b34ed0a42734138c8510322b",
            "_timestamp": "2019-07-05 11:41:54+08:00",
            "_commit_index": 454,
            "_changed_files_list": []
        },
        {
            "_sha_id": "556d34bbbccfad6a8df15ba1ebb7156ecb89b8bd",
            "_timestamp": "2019-11-25 10:26:46+08:00",
            "_commit_index": 486,
            "_changed_files_list": []
        },
        {
            "_sha_id": "68ac46b18e08a840e619cddb523d6b7ff4f73cf3",
            "_timestamp": "2019-12-30 14:13:33+08:00",
            "_commit_index": 502,
            "_changed_files_list": [
                {
                    "_file_name": "sylph-parser/src/main/java/ideal/sylph/parser/antlr/AstBuilder.java",
                    "_is_antlr_file": true,
                    "_enter_cnt": 0,
                    "_exit_cnt": 0,
                    "_visit_cnt": 22
                }
            ]
        },
        {
            "_sha_id": "607da73cc9fb27a8178cf6155c8fb919f7e03ed6",
            "_timestamp": "2019-12-18 22:56:53+08:00",
            "_commit_index": 494,
            "_changed_files_list": []
        },
        {
            "_sha_id": "4eb2c7c9e5b5d762f7c7f5e675901217566f305a",
            "_timestamp": "2019-12-19 22:10:51+08:00",
            "_commit_index": 498,
            "_changed_files_list": []
        },
        {
            "_sha_id": "0ccd321f8d2d728c1c0763a5f73d35d2b10c8632",
            "_timestamp": "2019-12-27 10:12:56+08:00",
            "_commit_index": 500,
            "_changed_files_list": []
        },
        {
            "_sha_id": "fabee0e8ba7a181cb86a926a268e0d600c79ec5d",
            "_timestamp": "2020-01-02 10:57:37+08:00",
            "_commit_index": 520,
            "_changed_files_list": [
                {
                    "_file_name": "sylph-parser/src/main/java/ideal/sylph/parser/antlr/AstBuilder.java",
                    "_is_antlr_file": true,
                    "_enter_cnt": 0,
                    "_exit_cnt": 0,
                    "_visit_cnt": 22
                }
            ]
        }
    ]
}